QtXuexiZhiLuV11/README.md
QtXuexiZhiLuV11/__init__.py
QtXuexiZhiLuV11/__main__.py
QtXuexiZhiLuV11/file.epub
QtXuexiZhiLuV11/index.html
QtXuexiZhiLuV11/css/__init__.py
QtXuexiZhiLuV11/css/annotations.css
QtXuexiZhiLuV11/css/main.css
QtXuexiZhiLuV11/css/normalize.css
QtXuexiZhiLuV11/css/popup.css
QtXuexiZhiLuV11/font/__init__.py
QtXuexiZhiLuV11/font/fontello.eot
QtXuexiZhiLuV11/font/fontello.svg
QtXuexiZhiLuV11/font/fontello.ttf
QtXuexiZhiLuV11/font/fontello.woff
QtXuexiZhiLuV11/img/__init__.py
QtXuexiZhiLuV11/img/annotator-glyph-sprite.png
QtXuexiZhiLuV11/img/annotator-icon-sprite.png
QtXuexiZhiLuV11/img/apple-touch-icon.png
QtXuexiZhiLuV11/img/cancelfullscreen.png
QtXuexiZhiLuV11/img/close.png
QtXuexiZhiLuV11/img/fullscreen.png
QtXuexiZhiLuV11/img/loader.gif
QtXuexiZhiLuV11/img/menu-icon.png
QtXuexiZhiLuV11/img/save.png
QtXuexiZhiLuV11/img/saved.png
QtXuexiZhiLuV11/img/settings-s.png
QtXuexiZhiLuV11/img/settings.png
QtXuexiZhiLuV11/img/star.png
QtXuexiZhiLuV11/js/__init__.py
QtXuexiZhiLuV11/js/epub.js
QtXuexiZhiLuV11/js/epub.min.js
QtXuexiZhiLuV11/js/epub.min.map
QtXuexiZhiLuV11/js/hooks.min.js
QtXuexiZhiLuV11/js/hooks.min.map
QtXuexiZhiLuV11/js/reader.js
QtXuexiZhiLuV11/js/reader.js.map
QtXuexiZhiLuV11/js/reader.min.js
QtXuexiZhiLuV11/js/reader.min.map
QtXuexiZhiLuV11/js/hooks/__init__.py
QtXuexiZhiLuV11/js/hooks/extensions/__init__.py
QtXuexiZhiLuV11/js/hooks/extensions/highlight.js
QtXuexiZhiLuV11/js/libs/__init__.py
QtXuexiZhiLuV11/js/libs/jquery.min.js
QtXuexiZhiLuV11/js/libs/localforage.min.js
QtXuexiZhiLuV11/js/libs/screenfull.js
QtXuexiZhiLuV11/js/libs/screenfull.min.js
QtXuexiZhiLuV11/js/libs/zip.min.js
QtXuexiZhiLuV11/js/plugins/__init__.py
QtXuexiZhiLuV11/js/plugins/hypothesis.js
QtXuexiZhiLuV11/js/plugins/search.js
qt_xuexi_zhi_lu_v1_1-2024.3.1.0.dist-info/METADATA
qt_xuexi_zhi_lu_v1_1-2024.3.1.0.dist-info/WHEEL
qt_xuexi_zhi_lu_v1_1-2024.3.1.0.dist-info/entry_points.txt
qt_xuexi_zhi_lu_v1_1-2024.3.1.0.dist-info/top_level.txt
qt_xuexi_zhi_lu_v1_1-2024.3.1.0.dist-info/RECORD
